MANIFEST.in
README.txt
setup.py
docs/HISTORY.txt
docs/LICENSE.txt
src/silva/__init__.py
src/silva.core.references.egg-info/PKG-INFO
src/silva.core.references.egg-info/SOURCES.txt
src/silva.core.references.egg-info/dependency_links.txt
src/silva.core.references.egg-info/entry_points.txt
src/silva.core.references.egg-info/namespace_packages.txt
src/silva.core.references.egg-info/not-zip-safe
src/silva.core.references.egg-info/requires.txt
src/silva.core.references.egg-info/top_level.txt
src/silva/core/__init__.py
src/silva/core/references/__init__.py
src/silva/core/references/configure.zcml
src/silva/core/references/graph.py
src/silva/core/references/interfaces.py
src/silva/core/references/keyreference.py
src/silva/core/references/reference.py
src/silva/core/references/service.png
src/silva/core/references/service.py
src/silva/core/references/utils.py
src/silva/core/references/service_templates/smilistbrokenreference.cpt
src/silva/core/references/service_templates/zmilistbrokenreference.pt
src/silva/core/references/tests/__init__.py
src/silva/core/references/tests/test_reference.py
src/silva/core/references/tests/test_service.py
src/silva/core/references/tests/test_silva.py
src/silva/core/references/tests/test_widget.py
src/silva/core/references/tests/widget/__init__.py
src/silva/core/references/tests/widget/multiple.txt
src/silva/core/references/tests/widget/simple.txt
src/silva/core/references/widgets/__init__.py
src/silva/core/references/widgets/formulator.py
src/silva/core/references/widgets/rest.py
src/silva/core/references/widgets/zeamform.py
src/silva/core/references/widgets/formulator_templates/reference_input.cpt
src/silva/core/references/widgets/rest_templates/referenceaddformtemplate.cpt
src/silva/core/references/widgets/rest_templates/referencelookup.cpt
src/silva/core/references/widgets/static/add.png
src/silva/core/references/widgets/static/delete.png
src/silva/core/references/widgets/static/edit.png
src/silva/core/references/widgets/static/folder_go.png
src/silva/core/references/widgets/static/reference.adding.js
src/silva/core/references/widgets/static/reference.adding.min.js
src/silva/core/references/widgets/static/reference.css
src/silva/core/references/widgets/static/reference.js
src/silva/core/references/widgets/static/reference.listing.js
src/silva/core/references/widgets/static/reference.listing.min.js
