Metadata-Version: 1.1
Name: silva.core.references
Version: 3.0.4
Summary: Define a reference engine usable by Silva content
Home-page: https://github.com/silvacms/silva.core.references
Author: Infrae
Author-email: info@infrae.com
License: BSD
Keywords: silva cms references zope
Platform: UNKNOWN
Classifier: Framework :: Zope2
Classifier: License :: OSI Approved :: BSD License
Classifier: Programming Language :: Python
Classifier: Topic :: Software Development :: Libraries :: Python Modules
